intentBox/__init__.py
intentBox/box.py
intentBox/container.py
intentBox/segmenter.py
intentBox/coreference/__init__.py
intentBox/coreference/base.py
intentBox/coreference/pronoun_postags.py
intentBox/coreference/remote.py
intentBox/intent_assistant/__init__.py
intentBox/intent_assistant/collision_detector.py
intentBox/lang/__init__.py
intentBox/lang/en.py
intentBox/lang/pt.py
intentBox/parsers/__init__.py
intentBox/parsers/adapt_extract.py
intentBox/parsers/nebulento_extract.py
intentBox/parsers/padacioso_extract.py
intentBox/parsers/padaos_extract.py
intentBox/parsers/padatious_extract.py
intentBox/parsers/palavreado_extract.py
intentBox/parsers/template.py
intentBox/segmentation/__init__.py
intentBox/segmentation/simple.py
intentBox/utils/__init__.py
intentBox/utils/bracket_expansion.py
intentBox/utils/log.py
CBintentBox-0.3.0a3.dist-info/LICENSE.md
CBintentBox-0.3.0a3.dist-info/METADATA
CBintentBox-0.3.0a3.dist-info/WHEEL
CBintentBox-0.3.0a3.dist-info/top_level.txt
CBintentBox-0.3.0a3.dist-info/RECORD
